bubot_selenium_scenario/__init__.py
bubot_selenium_scenario/buject/OcfDevice/subtype/SeleniumWorker/AriSefPtRes.py
bubot_selenium_scenario/buject/OcfDevice/subtype/SeleniumWorker/SeleniumWorker.json
bubot_selenium_scenario/buject/OcfDevice/subtype/SeleniumWorker/SeleniumWorker.py
bubot_selenium_scenario/buject/OcfDevice/subtype/SeleniumWorker/ToFirstGradeRes.py
bubot_selenium_scenario/buject/OcfDevice/subtype/SeleniumWorker/__init__.py
bubot_selenium_scenario/buject/SeleniumScenario/ScenarioExceptions.py
bubot_selenium_scenario/buject/SeleniumScenario/ScenarioPage.py
bubot_selenium_scenario/buject/SeleniumScenario/ScenarioState.py
bubot_selenium_scenario/buject/SeleniumScenario/SeleniumScenario.py
bubot_selenium_scenario-0.0.1.dist-info/LICENSE
bubot_selenium_scenario-0.0.1.dist-info/METADATA
bubot_selenium_scenario-0.0.1.dist-info/WHEEL
bubot_selenium_scenario-0.0.1.dist-info/top_level.txt
bubot_selenium_scenario-0.0.1.dist-info/RECORD
