Metadata-Version: 2.1
Name: bubot_selenium_scenario
Version: 0.0.1
Home-page: https://gitlab.com/razgovorov/bubot_selenium_scenario.git
Author: Razgovorov Mikhail
Author-email: 1338833@gmail.com
Classifier: Programming Language :: Python :: 3
Classifier: License :: OSI Approved :: MIT License
Classifier: Operating System :: OS Independent
Classifier: Framework :: AsyncIO
Requires-Python: >=3.8
License-File: LICENSE
Requires-Dist: selenium >=4
Requires-Dist: aioredis
Requires-Dist: packaging
Requires-Dist: webdriver-manager >=3.8
Requires-Dist: bubot-core ==4.0.0
Requires-Dist: bubot-helpers >=4.0.0
